Texo/Unet.py
Texo-0.0.3.dist-info/METADATA
Texo-0.0.3.dist-info/WHEEL
Texo-0.0.3.dist-info/top_level.txt
Texo-0.0.3.dist-info/RECORD
